{
"type": "FeatureCollection",
"name": "rooms_updated",
"crs": { "type": "name", "properties": { "name": "urn:ogc:def:crs:OGC:1.3:CRS84" } },
"features": [
{ "type": "Feature", "properties": { "id": 1, "Building": "JC Block", "Room": "JC301", "Floor": 3 }, "geometry": { "type": "Point", "coordinates": [ 80.507948, 16.463973 ] } },
{ "type": "Feature", "properties": { "id": 2, "Building": "Library Block", "Room": "LIB101", "Floor": 1 }, "geometry": { "type": "Point", "coordinates": [ 80.508600, 16.464400 ] } }
]
}
